swmr_tools/__init__.py
swmr_tools/chunk_utils.py
swmr_tools/chunksource.py
swmr_tools/datasource.py
swmr_tools/keyfollower.py
swmr_tools/utils.py
swmr_tools-0.9.0.dist-info/LICENSE
swmr_tools-0.9.0.dist-info/METADATA
swmr_tools-0.9.0.dist-info/WHEEL
swmr_tools-0.9.0.dist-info/top_level.txt
swmr_tools-0.9.0.dist-info/RECORD
